.DS_Store
etonger/__init__.py
etonger/ascmd.py
etonger/ehelper.py
etonger/etonger.py
etonger-1.1.8.dist-info/LICENSE
etonger-1.1.8.dist-info/METADATA
etonger-1.1.8.dist-info/WHEEL
etonger-1.1.8.dist-info/top_level.txt
etonger-1.1.8.dist-info/RECORD
