Metadata-Version: 2.1
Name: etonger
Version: 1.1.8
Summary: trading api
Home-page: https://github.com/robinshare/etonger
Author: RobinShare
Author-email: robinshare@foxmail.com
License: UNKNOWN
Platform: UNKNOWN
Classifier: Programming Language :: Python :: 3.9
Classifier: License :: OSI Approved :: MIT License
Classifier: Operating System :: OS Independent
Requires-Python: >=3.9
Requires-Dist: requests
